CHANGES.md
MANIFEST.in
README.md
pytest.ini
setup.py
tox.ini
elixr/__init__.py
elixr.sax.egg-info/PKG-INFO
elixr.sax.egg-info/SOURCES.txt
elixr.sax.egg-info/dependency_links.txt
elixr.sax.egg-info/not-zip-safe
elixr.sax.egg-info/requires.txt
elixr.sax.egg-info/top_level.txt
elixr/sax/__init__.py
elixr/sax/address.py
elixr/sax/meta.py
elixr/sax/mixins.py
elixr/sax/orgz.py
elixr/sax/types.py
elixr/sax/utils.py
elixr/sax/auth/__init__.py
elixr/sax/auth/models.py
elixr/sax/export/__init__.py
elixr/sax/export/importer.py