Metadata-Version: 1.0
Name: elixr.sax
Version: 0.3
Summary: Reusable types, models and utilities built around SQLAlchemy ORM
Home-page: https://github.com/hkmshb/elixr.sax
Author: Abdul-Hakeem Shaibu
Author-email: hkmshb@gmail.com
License: UNKNOWN
Keywords: elixr.sax,elixr SqlAlchemy eXtension
Platform: any
